{
  "tlId": "13kjs23t",
  "dj": "DJ Isaac",
  "stage": "EDC Las Vegas",
  "date": "2018-05-20",
  "year": 2018,
  "url": "https://www.1001tracklists.com/tracklist/13kjs23t/dj-isaac-wasteland-edc-las-vegas-united-states-2018-05-20.html",
  "djs": [
    {
      "name": "DJ Isaac",
      "slug": "djisaac"
    }
  ],
  "genre": "Afro House",
  "tracksIdentified": 0,
  "tracksTotal": 0,
  "duration": "",
  "tracks": [
    {
      "pos": "01",
      "artist": "TNT & DJ Isaac",
      "title": "Power Hour",
      "remix": "",
      "label": "Q-DANCE",
      "trackId": "3338322",
      "row": 1,
      "type": "normal",
      "cueTime": 0,
      "mediaIds": {
        "spotify": "365602",
        "youtube": "365602",
        "soundcloud": "365602",
        "appleMusic": "365602"
      },
      "blendGroup": null
    },
    {
      "pos": "02",
      "artist": "Wildstylez",
      "title": "Bounce Like This",
      "remix": "",
      "label": "ART OF CREATION",
      "trackId": "3338323",
      "row": 2,
      "type": "normal",
      "cueTime": 0,
      "mediaIds": {
        "spotify": "418755",
        "youtube": "418755",
        "soundcloud": "418755",
        "appleMusic": "418755"
      },
      "blendGroup": null
    },
    {
      "pos": "03",
      "artist": "Avicii ft. Aloe Blacc",
      "title": "Wake Me Up (Sound Rush 2018 Remix)",
      "remix": "",
      "label": "PRMD",
      "trackId": "3338324",
      "row": 3,
      "type": "normal",
      "cueTime": 0,
      "mediaIds": {
        "soundcloud": "419737"
      },
      "blendGroup": null
    },
    {
      "pos": "04",
      "artist": "DJ Isaac",
      "title": "Down With Me",
      "remix": "",
      "label": "DIRTY WORKZ",
      "trackId": "3338325",
      "row": 4,
      "type": "normal",
      "cueTime": 0,
      "mediaIds": {
        "spotify": "330170",
        "youtube": "330170",
        "soundcloud": "330170",
        "appleMusic": "330170"
      },
      "blendGroup": null
    },
    {
      "pos": "05",
      "artist": "DJ Isaac & Sound Rush",
      "title": "Find Me",
      "remix": "",
      "label": "DIRTY WORKZ",
      "trackId": "3338326",
      "row": 5,
      "type": "normal",
      "cueTime": 0,
      "mediaIds": {
        "spotify": "366527",
        "youtube": "366527",
        "soundcloud": "366527",
        "appleMusic": "366527"
      },
      "blendGroup": null
    },
    {
      "pos": "06",
      "artist": "Crypsis vs. Chain Reaction vs. Cyber",
      "title": "Break Down Low vs. The Record Breaking vs. MF Bass (D-Block & S-te-Fan Mashup)",
      "remix": "",
      "label": "MINUS IS MORE/DIRTY WORKZ",
      "trackId": "3338327",
      "row": 6,
      "type": "normal",
      "cueTime": 0,
      "mediaIds": null,
      "blendGroup": null
    },
    {
      "pos": "07",
      "artist": "TNT & DJ Isaac",
      "title": "Bitches 2016",
      "remix": "",
      "label": "DIRTY WORKZ",
      "trackId": "3338328",
      "row": 7,
      "type": "normal",
      "cueTime": 0,
      "mediaIds": {
        "spotify": "327880",
        "youtube": "327880",
        "appleMusic": "327880"
      },
      "blendGroup": null
    },
    {
      "pos": "08",
      "artist": "D-Block & S-te-Fan",
      "title": "Twilight Zone",
      "remix": "",
      "label": "Q-DANCE",
      "trackId": "3338329",
      "row": 8,
      "type": "normal",
      "cueTime": 0,
      "mediaIds": {
        "spotify": "391059",
        "youtube": "391059",
        "soundcloud": "391059",
        "appleMusic": "391059"
      },
      "blendGroup": null
    },
    {
      "pos": "09",
      "artist": "Yellow Claw & LNY TNZ",
      "title": "Last Night Ever (DJ Isaac Remix)",
      "remix": "",
      "label": "DIM MAK",
      "trackId": "3338330",
      "row": 9,
      "type": "normal",
      "cueTime": 0,
      "mediaIds": {
        "spotify": "173662",
        "youtube": "173662",
        "soundcloud": "173662",
        "appleMusic": "173662"
      },
      "blendGroup": null
    },
    {
      "pos": "10",
      "artist": "DJ Isaac & Crystal Lake",
      "title": "Stick Em (Hard Mix)",
      "remix": "",
      "label": "DUTCH MASTER WORKS (2DUTCH)",
      "trackId": "3338331",
      "row": 10,
      "type": "normal",
      "cueTime": 0,
      "mediaIds": {
        "spotify": "258412",
        "youtube": "258412",
        "soundcloud": "258412",
        "appleMusic": "258412"
      },
      "blendGroup": null
    },
    {
      "pos": "11",
      "artist": "Armin van Buuren vs. Vini Vici ft. Hilight Tribe",
      "title": "Great Spirit (Wildstylez Remix)",
      "remix": "",
      "label": "ARMIND (ARMADA)",
      "trackId": "3338332",
      "row": 11,
      "type": "normal",
      "cueTime": 0,
      "mediaIds": {
        "spotify": "355607",
        "youtube": "355607",
        "soundcloud": "355607",
        "appleMusic": "355607"
      },
      "blendGroup": null
    },
    {
      "pos": "12",
      "artist": "D-Block & S-te-Fan",
      "title": "In The Dark",
      "remix": "",
      "label": "SCANTRAXX EVOLUTIONZ",
      "trackId": "3338333",
      "row": 12,
      "type": "normal",
      "cueTime": 0,
      "mediaIds": {
        "spotify": "379895",
        "youtube": "379895",
        "soundcloud": "379895",
        "appleMusic": "379895"
      },
      "blendGroup": null
    },
    {
      "pos": "13",
      "artist": "TNT & DJ Isaac",
      "title": "The Realm",
      "remix": "",
      "label": "TITANIC",
      "trackId": "3338334",
      "row": 13,
      "type": "normal",
      "cueTime": 0,
      "mediaIds": {
        "spotify": "421514",
        "youtube": "421514",
        "soundcloud": "421514",
        "appleMusic": "421514"
      },
      "blendGroup": null
    },
    {
      "pos": "14",
      "artist": "Psyko Punkz & DJ Isaac & Sound Rush",
      "title": "Unbreakable",
      "remix": "",
      "label": "DIRTY WORKZ",
      "trackId": "3338335",
      "row": 14,
      "type": "normal",
      "cueTime": 0,
      "mediaIds": {
        "spotify": "404598",
        "youtube": "404598",
        "appleMusic": "404598"
      },
      "blendGroup": null
    },
    {
      "pos": "15",
      "artist": "Sub Sonik",
      "title": "Sandstorm",
      "remix": "",
      "label": "FREE/DWX COVERS",
      "trackId": "3338336",
      "row": 15,
      "type": "normal",
      "cueTime": 0,
      "mediaIds": {
        "spotify": "307297",
        "youtube": "307297",
        "soundcloud": "307297",
        "appleMusic": "307297"
      },
      "blendGroup": null
    },
    {
      "pos": "16",
      "artist": "TNT & DJ Isaac",
      "title": "Digital Nation",
      "remix": "",
      "label": "TITANIC",
      "trackId": "3338337",
      "row": 16,
      "type": "normal",
      "cueTime": 0,
      "mediaIds": {
        "spotify": "211358",
        "youtube": "211358",
        "soundcloud": "211358",
        "appleMusic": "211358"
      },
      "blendGroup": null
    },
    {
      "pos": "17",
      "artist": "Dash Berlin ft. Do",
      "title": "Heaven (DJ Isaac Remix)",
      "remix": "",
      "label": "ARMADA",
      "trackId": "3338338",
      "row": 17,
      "type": "normal",
      "cueTime": 0,
      "mediaIds": {
        "spotify": "352002",
        "youtube": "352002",
        "appleMusic": "352002"
      },
      "blendGroup": null
    },
    {
      "pos": "18",
      "artist": "DJ Isaac",
      "title": "Let There Be Hardstyle",
      "remix": "",
      "label": "DIRTY WORKZ",
      "trackId": "3338339",
      "row": 18,
      "type": "normal",
      "cueTime": 0,
      "mediaIds": {
        "spotify": "398505",
        "youtube": "398505",
        "soundcloud": "398505",
        "appleMusic": "398505"
      },
      "blendGroup": null
    },
    {
      "pos": "19",
      "artist": "Donkey Rollers",
      "title": "The Fusion Of Sound (DJ Isaac Remix)",
      "remix": "",
      "label": "FUSION RECORDS",
      "trackId": "3338340",
      "row": 19,
      "type": "normal",
      "cueTime": 0,
      "mediaIds": {
        "spotify": "355267",
        "youtube": "355267",
        "soundcloud": "355267",
        "appleMusic": "355267"
      },
      "blendGroup": null
    },
    {
      "pos": "20",
      "artist": "DJ Isaac",
      "title": "Burn (Sub Zero Project Remix)",
      "remix": "",
      "label": "DIRTY WORKZ",
      "trackId": "3338341",
      "row": 20,
      "type": "normal",
      "cueTime": 0,
      "mediaIds": {
        "spotify": "370386",
        "youtube": "370386",
        "soundcloud": "370386",
        "appleMusic": "370386"
      },
      "blendGroup": null
    }
  ],
  "recordings": [
    {
      "platform": "youtube",
      "idMedia": "798262",
      "idSource": "13",
      "url": "https://www.youtube.com/watch?v=4WtdjembB7o"
    }
  ],
  "scrapedAt": "2026-04-08T06:32:50.684Z",
  "scrapeVersion": 2
}