{
  "tlId": "2hkyf469",
  "dj": "Dom Dolla",
  "stage": "EDC Mexico",
  "date": "2023-02-24",
  "year": 2023,
  "url": "https://www.1001tracklists.com/tracklist/2hkyf469/dom-dolla-circuitgrounds-edc-mexico-2023-02-24.html",
  "djs": [
    {
      "name": "Dom Dolla",
      "slug": "domdolla"
    }
  ],
  "genre": "Afro House",
  "tracksIdentified": 0,
  "tracksTotal": 0,
  "duration": "",
  "tracks": [
    {
      "pos": "01",
      "artist": "Gorillaz ft. Tame Impala & Bootie Brown",
      "title": "New Gold (Dom Dolla Remix)",
      "remix": "",
      "label": "PARLOPHONE (WARNER MUSIC)",
      "trackId": "8764118",
      "row": 1,
      "type": "normal",
      "cueTime": 0,
      "mediaIds": {
        "spotify": "843999",
        "youtube": "843999",
        "soundcloud": "843999",
        "appleMusic": "843999"
      },
      "blendGroup": null
    },
    {
      "pos": "02",
      "artist": "Chris Lake & Green Velvet",
      "title": "Deceiver (VIP)",
      "remix": "",
      "label": "BLACK BOOK",
      "trackId": "8804078",
      "row": 2,
      "type": "normal",
      "cueTime": 0,
      "mediaIds": {
        "spotify": "720539",
        "youtube": "720539",
        "soundcloud": "720539",
        "appleMusic": "720539"
      },
      "blendGroup": null
    },
    {
      "pos": "03",
      "artist": "Solardo vs. Dom Dolla",
      "title": "Riser vs. San Frandisco (Dom Dolla Edit)",
      "remix": "",
      "label": "",
      "trackId": "8766448",
      "row": 3,
      "type": "normal",
      "cueTime": 0,
      "mediaIds": null,
      "blendGroup": null
    },
    {
      "pos": "04",
      "artist": "Tiga",
      "title": "Mind Dimension (Kölsch Remix)",
      "remix": "",
      "label": "IPSO/DIFFERENT",
      "trackId": "8766449",
      "row": 4,
      "type": "normal",
      "cueTime": 0,
      "mediaIds": {
        "spotify": "791960",
        "youtube": "791960",
        "soundcloud": "791960",
        "appleMusic": "791960"
      },
      "blendGroup": null
    },
    {
      "pos": "05",
      "artist": "Skrillex & Fred again.. & Flowdan",
      "title": "Rumble (Pickle Remix)",
      "remix": "",
      "label": "",
      "trackId": "9026823",
      "row": 5,
      "type": "normal",
      "cueTime": 0,
      "mediaIds": {
        "youtube": "857980",
        "soundcloud": "857980"
      },
      "blendGroup": null
    },
    {
      "pos": "06",
      "artist": "RÜFÜS DU SOL",
      "title": "On My Knees (Cassian Remix)",
      "remix": "",
      "label": "ROSE AVENUE",
      "trackId": "9026824",
      "row": 6,
      "type": "normal",
      "cueTime": 0,
      "mediaIds": {
        "spotify": "798337",
        "youtube": "798337",
        "soundcloud": "798337",
        "appleMusic": "798337"
      },
      "blendGroup": null
    },
    {
      "pos": "07",
      "artist": "John Summit",
      "title": "Revolution",
      "remix": "",
      "label": "EXPERTS ONLY",
      "trackId": "8766447",
      "row": 7,
      "type": "normal",
      "cueTime": 0,
      "mediaIds": {
        "spotify": "851539",
        "youtube": "851539",
        "soundcloud": "851539",
        "appleMusic": "851539"
      },
      "blendGroup": null
    },
    {
      "pos": "08",
      "artist": "ROSALÍA",
      "title": "Bizcochito",
      "remix": "",
      "label": "COLUMBIA (SONY)",
      "trackId": "8759546",
      "row": 8,
      "type": "normal",
      "cueTime": 24,
      "mediaIds": {
        "spotify": "782375",
        "youtube": "782375",
        "soundcloud": "782375",
        "appleMusic": "782375"
      },
      "blendGroup": null
    },
    {
      "pos": "09",
      "artist": "MK & Dom Dolla",
      "title": "Rhyme Dust",
      "remix": "",
      "label": "COLUMBIA/ULTRA",
      "trackId": "8759547",
      "row": 9,
      "type": "normal",
      "cueTime": 118,
      "mediaIds": {
        "spotify": "867915",
        "youtube": "867915",
        "soundcloud": "867915",
        "appleMusic": "867915"
      },
      "blendGroup": null
    },
    {
      "pos": "10",
      "artist": "Fred again.. & Skrillex & Four Tet ft. Lil Baby",
      "title": "Baby Again..",
      "remix": "",
      "label": "OWSLA/ATLANTIC",
      "trackId": "8759548",
      "row": 10,
      "type": "normal",
      "cueTime": 326,
      "mediaIds": {
        "spotify": "819603",
        "youtube": "819603",
        "soundcloud": "819603",
        "appleMusic": "819603"
      },
      "blendGroup": null
    },
    {
      "pos": "11",
      "artist": "TCTS vs. Sonny Fodera & Dom Dolla",
      "title": "Lights Out vs. Moving Blind (Dom Dolla Edit)",
      "remix": "",
      "label": "SOLOTOKO/SWEAT IT OUT!/MUSICAL FREEDOM",
      "trackId": "8759549",
      "row": 11,
      "type": "normal",
      "cueTime": 519,
      "mediaIds": null,
      "blendGroup": null
    },
    {
      "pos": "12",
      "artist": "Sevek & Mc Th",
      "title": "Assim",
      "remix": "",
      "label": "SPINNIN' DEEP",
      "trackId": "8759550",
      "row": 12,
      "type": "normal",
      "cueTime": 677,
      "mediaIds": {
        "spotify": "848671",
        "youtube": "848671",
        "soundcloud": "848671",
        "appleMusic": "848671"
      },
      "blendGroup": null
    },
    {
      "pos": "13",
      "artist": "Piero Pirupa",
      "title": "We Don't Need",
      "remix": "",
      "label": "SPINNIN' DEEP",
      "trackId": "8759551",
      "row": 13,
      "type": "normal",
      "cueTime": 805,
      "mediaIds": {
        "spotify": "777227",
        "youtube": "777227",
        "soundcloud": "777227",
        "appleMusic": "777227"
      },
      "blendGroup": null
    },
    {
      "pos": "14",
      "artist": "GENESI",
      "title": "Everything You Have Done (MEDUZA Edit)",
      "remix": "",
      "label": "AETERNA",
      "trackId": "8759553",
      "row": 14,
      "type": "normal",
      "cueTime": 936,
      "mediaIds": {
        "spotify": "870126",
        "youtube": "870126",
        "soundcloud": "870126",
        "appleMusic": "870126"
      },
      "blendGroup": null
    },
    {
      "pos": "15",
      "artist": "Eli Brown",
      "title": "Killer",
      "remix": "",
      "label": "POLYDOR",
      "trackId": "8759554",
      "row": 15,
      "type": "normal",
      "cueTime": 1193,
      "mediaIds": {
        "spotify": "617922",
        "youtube": "617922",
        "soundcloud": "617922",
        "appleMusic": "617922"
      },
      "blendGroup": null
    },
    {
      "pos": "16",
      "artist": "Dom Dolla ft. Clementine Douglas",
      "title": "Miracle Maker",
      "remix": "(VIP Intro)",
      "label": "THREE SIX ZERO/SONY",
      "trackId": "8764119",
      "row": 16,
      "type": "normal",
      "cueTime": 0,
      "mediaIds": {
        "spotify": "791747",
        "youtube": "791747",
        "soundcloud": "791747",
        "appleMusic": "791747"
      },
      "blendGroup": null
    },
    {
      "pos": "17",
      "artist": "Da Hool",
      "title": "Meet Her At The Love Parade (Dom Dolla & Torren Foot Remix)",
      "remix": "",
      "label": "KOSMO",
      "trackId": "9026825",
      "row": 17,
      "type": "normal",
      "cueTime": 0,
      "mediaIds": {
        "youtube": "782945"
      },
      "blendGroup": [
        {
          "artist": "Da Hool",
          "title": "Meet Her At The Love Parade (Dom Dolla & Torren Foot Remix)",
          "remix": "",
          "trackId": "9026825"
        },
        {
          "artist": "Faithless",
          "title": "Insomnia (Acappella)",
          "remix": "",
          "trackId": "9026826"
        }
      ]
    },
    {
      "pos": "w/",
      "artist": "Faithless",
      "title": "Insomnia (Acappella)",
      "remix": "",
      "label": "CHEEKY",
      "trackId": "9026826",
      "row": 17,
      "type": "blend",
      "cueTime": 0,
      "mediaIds": {
        "spotify": "1515",
        "youtube": "1515",
        "soundcloud": "1515",
        "appleMusic": "1515"
      }
    },
    {
      "pos": "18",
      "artist": "Dom Dolla",
      "title": "Take It",
      "remix": "",
      "label": "SWEAT IT OUT!",
      "trackId": "8759555",
      "row": 18,
      "type": "normal",
      "cueTime": 0,
      "mediaIds": {
        "spotify": "429941",
        "youtube": "429941",
        "soundcloud": "429941",
        "appleMusic": "429941"
      },
      "blendGroup": null
    },
    {
      "pos": "19",
      "artist": "Dom Dolla & Go Freek",
      "title": "Define",
      "remix": "",
      "label": "SWEAT IT OUT!",
      "trackId": "9026827",
      "row": 19,
      "type": "normal",
      "cueTime": 0,
      "mediaIds": {
        "spotify": "261807",
        "youtube": "261807",
        "soundcloud": "261807",
        "appleMusic": "261807"
      },
      "blendGroup": null
    }
  ],
  "recordings": [
    {
      "platform": "youtube",
      "idMedia": "3236322",
      "idSource": "13",
      "url": "https://www.youtube.com/watch?v=ROxFPxM6AZ0"
    }
  ],
  "scrapedAt": "2026-04-08T17:08:54.702Z",
  "scrapeVersion": 2
}