{
  "tlId": "2tv2py1",
  "dj": "Headhunterz",
  "stage": "Q-Dance Stage",
  "date": "2012-06-09",
  "year": 2012,
  "url": "https://www.1001tracklists.com/tracklist/2tv2py1/headhunterz-q-dance-stage-edc-las-vegas-united-states-2012-06-09.html",
  "djs": [
    {
      "name": "Headhunterz",
      "slug": "headhunterz"
    }
  ],
  "genre": "Afro House",
  "tracksIdentified": 0,
  "tracksTotal": 0,
  "duration": "",
  "tracks": [
    {
      "pos": "01",
      "artist": "Headhunterz",
      "title": "Psychedelic Sunshine",
      "remix": "",
      "label": "SCANTRAXX/SCANTRAXX RELOADED/ITWT (BLACK HOLE)",
      "trackId": "243597",
      "row": 1,
      "type": "normal",
      "cueTime": 0,
      "mediaIds": null,
      "blendGroup": null
    },
    {
      "pos": "02",
      "artist": "Blutonium Boy",
      "title": "Make It Loud (Headhunterz Remix)",
      "remix": "",
      "label": "BLUTONIUM",
      "trackId": "243598",
      "row": 2,
      "type": "normal",
      "cueTime": 0,
      "mediaIds": {
        "spotify": "602447",
        "youtube": "602447",
        "soundcloud": "602447",
        "appleMusic": "602447"
      },
      "blendGroup": null
    },
    {
      "pos": "03",
      "artist": "Headhunterz",
      "title": "Megasound",
      "remix": "",
      "label": "SCANTRAXX RELOADED",
      "trackId": "243599",
      "row": 3,
      "type": "normal",
      "cueTime": 0,
      "mediaIds": {
        "spotify": "80063",
        "appleMusic": "80063"
      },
      "blendGroup": null
    },
    {
      "pos": "04",
      "artist": "Kaskade ft. Neon Trees",
      "title": "Lessons In Love (Headhunterz Remix)",
      "remix": "",
      "label": "ULTRA",
      "trackId": "243600",
      "row": 4,
      "type": "normal",
      "cueTime": 0,
      "mediaIds": {
        "spotify": "76783",
        "youtube": "76783",
        "soundcloud": "76783",
        "appleMusic": "76783"
      },
      "blendGroup": null
    },
    {
      "pos": "05",
      "artist": "Code Black & NitrouZ",
      "title": "Can't Hold Me Back",
      "remix": "",
      "label": "FUSION RECORDS",
      "trackId": "243601",
      "row": 5,
      "type": "normal",
      "cueTime": 0,
      "mediaIds": {
        "spotify": "80064",
        "youtube": "80064",
        "soundcloud": "80064",
        "appleMusic": "80064"
      },
      "blendGroup": null
    },
    {
      "pos": "06",
      "artist": "Headhunterz",
      "title": "Scrap Attack (Defqon.1 2009 Anthem) (BMW Edit)",
      "remix": "",
      "label": "Q-DANCE",
      "trackId": "243602",
      "row": 6,
      "type": "normal",
      "cueTime": 0,
      "mediaIds": null,
      "blendGroup": null
    },
    {
      "pos": "07",
      "artist": "Headhunterz",
      "title": "From Within",
      "remix": "",
      "label": "SCANTRAXX RELOADED",
      "trackId": "243603",
      "row": 7,
      "type": "normal",
      "cueTime": 0,
      "mediaIds": {
        "spotify": "80067",
        "youtube": "80067",
        "appleMusic": "80067"
      },
      "blendGroup": null
    },
    {
      "pos": "08",
      "artist": "Builder",
      "title": "Her Voice (Headhunterz Remix)",
      "remix": "",
      "label": "DANCE POLLUTION",
      "trackId": "243604",
      "row": 8,
      "type": "normal",
      "cueTime": 0,
      "mediaIds": {
        "spotify": "80069",
        "youtube": "80069",
        "appleMusic": "80069"
      },
      "blendGroup": null
    },
    {
      "pos": "09",
      "artist": "Headhunterz & Malukah",
      "title": "Reignite",
      "remix": "",
      "label": "HARD WITH STYLE",
      "trackId": "243605",
      "row": 9,
      "type": "normal",
      "cueTime": 0,
      "mediaIds": {
        "spotify": "80070",
        "youtube": "80070",
        "soundcloud": "80070",
        "appleMusic": "80070"
      },
      "blendGroup": null
    },
    {
      "pos": "10",
      "artist": "Geck-o",
      "title": "It's What We Are (Headhunterz Edit)",
      "remix": "",
      "label": "THERACORDS",
      "trackId": "243606",
      "row": 10,
      "type": "normal",
      "cueTime": 0,
      "mediaIds": {
        "spotify": "80072",
        "youtube": "80072",
        "appleMusic": "80072"
      },
      "blendGroup": null
    },
    {
      "pos": "11",
      "artist": "Plan B",
      "title": "Love Goes Down (Doctor P Remix)",
      "remix": "",
      "label": "ATLANTIC (WARNER MUSIC)",
      "trackId": "243607",
      "row": 11,
      "type": "normal",
      "cueTime": 0,
      "mediaIds": {
        "spotify": "28606",
        "youtube": "28606",
        "soundcloud": "28606",
        "appleMusic": "28606"
      },
      "blendGroup": null
    },
    {
      "pos": "12",
      "artist": "Chuckie ft. Gregor Salto",
      "title": "What Happens In Vegas (Headhunterz Remix)",
      "remix": "",
      "label": "CR2",
      "trackId": "243608",
      "row": 12,
      "type": "normal",
      "cueTime": 0,
      "mediaIds": {
        "youtube": "80073"
      },
      "blendGroup": null
    },
    {
      "pos": "13",
      "artist": "Project One",
      "title": "Rate Reducer (Headhunterz Remix)",
      "remix": "",
      "label": "SCANTRAXX RELOADED",
      "trackId": "243609",
      "row": 13,
      "type": "normal",
      "cueTime": 0,
      "mediaIds": {
        "spotify": "80075",
        "youtube": "80075",
        "soundcloud": "80075",
        "appleMusic": "80075"
      },
      "blendGroup": null
    },
    {
      "pos": "14",
      "artist": "Chuckie",
      "title": "Let The Bass Kick (Headhunterz Edit)",
      "remix": "",
      "label": "DIRTY DUTCH",
      "trackId": "243610",
      "row": 14,
      "type": "normal",
      "cueTime": 0,
      "mediaIds": {
        "youtube": "75909"
      },
      "blendGroup": null
    },
    {
      "pos": "15",
      "artist": "Headhunterz",
      "title": "Rock Civilization",
      "remix": "",
      "label": "HARD WITH STYLE ORIGINS",
      "trackId": "243611",
      "row": 15,
      "type": "normal",
      "cueTime": 0,
      "mediaIds": {
        "spotify": "80076",
        "youtube": "80076",
        "soundcloud": "80076",
        "appleMusic": "80076"
      },
      "blendGroup": null
    },
    {
      "pos": "16",
      "artist": "Headhunterz & Wildstylez & Noisecontrollers & Wildstylez",
      "title": "Tonight",
      "remix": "",
      "label": "SCANTRAXX RELOADED",
      "trackId": "243612",
      "row": 16,
      "type": "normal",
      "cueTime": 0,
      "mediaIds": {
        "spotify": "69592",
        "youtube": "69592",
        "appleMusic": "69592"
      },
      "blendGroup": null
    },
    {
      "pos": "17",
      "artist": "Headhunterz & Brennan Heart",
      "title": "The Mf Point Of Perfection",
      "remix": "",
      "label": "SCANTRAXX",
      "trackId": "243613",
      "row": 17,
      "type": "normal",
      "cueTime": 0,
      "mediaIds": {
        "spotify": "80077",
        "youtube": "80077",
        "appleMusic": "80077"
      },
      "blendGroup": null
    },
    {
      "pos": "18",
      "artist": "Headhunterz",
      "title": "Dragonborn",
      "remix": "",
      "label": "FREE",
      "trackId": "243614",
      "row": 18,
      "type": "normal",
      "cueTime": 0,
      "mediaIds": {
        "spotify": "80078",
        "youtube": "80078",
        "appleMusic": "80078"
      },
      "blendGroup": null
    },
    {
      "pos": "19",
      "artist": "Proppy & Heady",
      "title": "Summer Of Hardstyle",
      "remix": "",
      "label": "SCANTRAXX",
      "trackId": "243615",
      "row": 19,
      "type": "normal",
      "cueTime": 0,
      "mediaIds": {
        "spotify": "80079",
        "youtube": "80079",
        "appleMusic": "80079"
      },
      "blendGroup": null
    },
    {
      "pos": "20",
      "artist": "Frontliner",
      "title": "Dream Dust",
      "remix": "",
      "label": "SCANTRAXX",
      "trackId": "243616",
      "row": 20,
      "type": "normal",
      "cueTime": 0,
      "mediaIds": {
        "spotify": "80080",
        "youtube": "80080",
        "soundcloud": "80080",
        "appleMusic": "80080"
      },
      "blendGroup": null
    },
    {
      "pos": "21",
      "artist": "Hardwell",
      "title": "Spaceman (Headhunterz Remix)",
      "remix": "",
      "label": "REVEALED",
      "trackId": "243617",
      "row": 21,
      "type": "normal",
      "cueTime": 0,
      "mediaIds": {
        "spotify": "70752",
        "youtube": "70752",
        "soundcloud": "70752",
        "appleMusic": "70752"
      },
      "blendGroup": null
    },
    {
      "pos": "22",
      "artist": "Headhunterz & Wildstylez ft. Mc Villain",
      "title": "Stuck In Ur Head",
      "remix": "",
      "label": "SCANTRAXX",
      "trackId": "243618",
      "row": 22,
      "type": "normal",
      "cueTime": 0,
      "mediaIds": {
        "spotify": "80081",
        "youtube": "80081",
        "appleMusic": "80081"
      },
      "blendGroup": null
    },
    {
      "pos": "23",
      "artist": "Noisecontrollers & Toneshifterz",
      "title": "Jaydee (Noisecontrollers 2012 Edit)",
      "remix": "",
      "label": "FUSION RECORDS",
      "trackId": "243619",
      "row": 23,
      "type": "normal",
      "cueTime": 0,
      "mediaIds": {
        "spotify": "80083",
        "appleMusic": "80083"
      },
      "blendGroup": null
    },
    {
      "pos": "24",
      "artist": "Headhunterz",
      "title": "Subsonic",
      "remix": "",
      "label": "SCANTRAXX RELOADED",
      "trackId": "243620",
      "row": 24,
      "type": "normal",
      "cueTime": 0,
      "mediaIds": {
        "spotify": "80084",
        "youtube": "80084",
        "soundcloud": "80084",
        "appleMusic": "80084"
      },
      "blendGroup": null
    },
    {
      "pos": "25",
      "artist": "Project One",
      "title": "The Art Of Creation",
      "remix": "",
      "label": "SCANTRAXX RELOADED",
      "trackId": "243621",
      "row": 25,
      "type": "normal",
      "cueTime": 0,
      "mediaIds": {
        "spotify": "80085",
        "youtube": "80085",
        "soundcloud": "80085",
        "appleMusic": "80085"
      },
      "blendGroup": null
    },
    {
      "pos": "26",
      "artist": "Alpha²",
      "title": "From The Rain",
      "remix": "",
      "label": "A² (SCANTRAXX)",
      "trackId": "243622",
      "row": 26,
      "type": "normal",
      "cueTime": 0,
      "mediaIds": {
        "spotify": "276604",
        "youtube": "276604",
        "soundcloud": "276604",
        "appleMusic": "276604"
      },
      "blendGroup": null
    }
  ],
  "recordings": [
    {
      "platform": "source_16",
      "idMedia": "37862",
      "idSource": "16",
      "url": "https://www.mixcloud.com/edmtunes"
    }
  ],
  "scrapedAt": "2026-04-08T13:33:16.908Z",
  "scrapeVersion": 2
}