{
  "tlId": "16bvhyl1",
  "dj": "Nicole Moudaber",
  "stage": "In The MOOD 209 (",
  "date": "2018-04-29",
  "year": 2018,
  "genre": "Afro House",
  "tracksIdentified": 0,
  "tracksTotal": 0,
  "duration": "57m",
  "views": 12,
  "likes": 1,
  "url": "https://www.1001tracklists.com/tracklist/16bvhyl1/nicole-moudaber-in-the-mood-209-ultra-music-festival-miami-united-states-2018-04-29.html",
  "tracks": [
    {
      "pos": "01",
      "artist": "Parce",
      "title": "Sweet Tings",
      "remix": "",
      "label": "LOW GROOVE",
      "trackId": "3230299",
      "row": 1,
      "type": "normal",
      "cueTime": 0,
      "mediaIds": {
        "youtube": "407521",
        "soundcloud": "407521"
      },
      "blendGroup": null
    },
    {
      "pos": "02",
      "artist": "Jon Rundell",
      "title": "Jack the Bass",
      "remix": "",
      "label": "ETCH",
      "trackId": "3230300",
      "row": 2,
      "type": "normal",
      "cueTime": 0,
      "mediaIds": {
        "spotify": "407493",
        "soundcloud": "407493"
      },
      "blendGroup": null
    },
    {
      "pos": "03",
      "artist": "Cuartero",
      "title": "Enderezado (Cocodrills Remix)",
      "remix": "",
      "label": "CUARTERO CONCEPT",
      "trackId": "3230301",
      "row": 3,
      "type": "normal",
      "cueTime": 0,
      "mediaIds": {
        "youtube": "492832"
      },
      "blendGroup": null
    },
    {
      "pos": "04",
      "artist": "Golf Clap & Jojo Angel & Matteo Rosolare",
      "title": "Everybody",
      "remix": "",
      "label": "RELIEF",
      "trackId": "3230302",
      "row": 4,
      "type": "normal",
      "cueTime": 0,
      "mediaIds": {
        "spotify": "354092",
        "youtube": "354092",
        "soundcloud": "354092"
      },
      "blendGroup": null
    },
    {
      "pos": "05",
      "artist": "Agent Orange DJ",
      "title": "I'm Free",
      "remix": "",
      "label": "KISM",
      "trackId": "3230303",
      "row": 5,
      "type": "normal",
      "cueTime": 0,
      "mediaIds": {
        "spotify": "407494",
        "youtube": "407494",
        "soundcloud": "407494",
        "appleMusic": "407494"
      },
      "blendGroup": null
    },
    {
      "pos": "06",
      "artist": "CamelPhat",
      "title": "101",
      "remix": "",
      "label": "RELIEF",
      "trackId": "3230304",
      "row": 6,
      "type": "normal",
      "cueTime": 0,
      "mediaIds": {
        "spotify": "353126",
        "youtube": "353126",
        "soundcloud": "353126",
        "appleMusic": "353126"
      },
      "blendGroup": null
    },
    {
      "pos": "07",
      "artist": "Anthony Rother",
      "title": "Generation Electro",
      "remix": "",
      "label": "OMNIDISC",
      "trackId": "3230305",
      "row": 7,
      "type": "normal",
      "cueTime": 0,
      "mediaIds": {
        "youtube": "392208"
      },
      "blendGroup": null
    },
    {
      "pos": "08",
      "artist": "Carlo Lio",
      "title": "All She Wants",
      "remix": "",
      "label": "TURBO",
      "trackId": "3230306",
      "row": 8,
      "type": "normal",
      "cueTime": 0,
      "mediaIds": {
        "spotify": "384262",
        "soundcloud": "384262",
        "appleMusic": "384262"
      },
      "blendGroup": null
    },
    {
      "pos": "09",
      "artist": "ANOTR",
      "title": "Let Me Tell You",
      "remix": "",
      "label": "NO ART",
      "trackId": "3230307",
      "row": 9,
      "type": "normal",
      "cueTime": 0,
      "mediaIds": {
        "spotify": "392694",
        "youtube": "392694",
        "soundcloud": "392694",
        "appleMusic": "392694"
      },
      "blendGroup": null
    },
    {
      "pos": "10",
      "artist": "Carlo Lio",
      "title": "Real Cats (2000 And One Remix)",
      "remix": "",
      "label": "100% PURE",
      "trackId": "3230308",
      "row": 10,
      "type": "normal",
      "cueTime": 0,
      "mediaIds": {
        "spotify": "389595",
        "soundcloud": "389595",
        "appleMusic": "389595"
      },
      "blendGroup": null
    }
  ],
  "djs": [
    {
      "name": "Nicole Moudaber",
      "slug": "nicolemoudaber"
    }
  ],
  "recordings": [
    {
      "platform": "source_16",
      "idMedia": "779056",
      "idSource": "16",
      "url": "https://www.mixcloud.com/nicolemoudaber"
    },
    {
      "platform": "source_16",
      "idMedia": "1895303",
      "idSource": "16",
      "url": "https://www.mixcloud.com/UMFradio"
    },
    {
      "platform": "youtube",
      "idMedia": "757488",
      "idSource": "13",
      "url": "https://www.youtube.com/watch?v=-pdk3CS5SVI"
    },
    {
      "platform": "source_25",
      "idMedia": "753707",
      "idSource": "25",
      "url": "https://www.youtube.com/watch?v=embed_clean"
    },
    {
      "platform": "source_25",
      "idMedia": "753707",
      "idSource": "25",
      "url": "https://www.youtube.com/watch?v=embed_clean"
    }
  ],
  "scrapedAt": "2026-04-08T05:22:41.142Z",
  "scrapeVersion": 2
}