{
  "tlId": "1s7gkxzt",
  "dj": "Excision",
  "stage": "EDC Las Vegas",
  "date": "2022-05-22",
  "year": 2022,
  "url": "https://www.1001tracklists.com/tracklist/1s7gkxzt/excision-circuitgrounds-edc-las-vegas-united-states-2022-05-22.html",
  "djs": [
    {
      "name": "Excision",
      "slug": "excision"
    }
  ],
  "genre": "Afro House",
  "tracksIdentified": 0,
  "tracksTotal": 0,
  "duration": "",
  "tracks": [
    {
      "pos": "01",
      "artist": "Excision & Sullivan King",
      "title": "Bass To The Dome",
      "remix": "",
      "label": "SUBSIDIA",
      "trackId": "7718421",
      "row": 1,
      "type": "normal",
      "cueTime": 0,
      "mediaIds": {
        "spotify": "919803",
        "youtube": "919803",
        "soundcloud": "919803",
        "appleMusic": "919803"
      },
      "blendGroup": null
    },
    {
      "pos": "02",
      "artist": "High Zombie & FREAKY",
      "title": "Attention",
      "remix": "",
      "label": "SUBSIDIA",
      "trackId": "7718422",
      "row": 2,
      "type": "normal",
      "cueTime": 0,
      "mediaIds": {
        "spotify": "765611",
        "youtube": "765611",
        "soundcloud": "765611",
        "appleMusic": "765611"
      },
      "blendGroup": null
    },
    {
      "pos": "03",
      "artist": "Deadlyft",
      "title": "MAAD CITY",
      "remix": "",
      "label": "AFTERMATH ENTERTAINMENT (INTERSCOPE)",
      "trackId": "7718423",
      "row": 3,
      "type": "normal",
      "cueTime": 0,
      "mediaIds": {
        "spotify": "803871",
        "youtube": "803871",
        "soundcloud": "803871",
        "appleMusic": "803871"
      },
      "blendGroup": null
    },
    {
      "pos": "04",
      "artist": "Excision & Wooli",
      "title": "Lockdown",
      "remix": "",
      "label": "EXCISION",
      "trackId": "7718424",
      "row": 4,
      "type": "normal",
      "cueTime": 0,
      "mediaIds": {
        "spotify": "515655",
        "youtube": "515655",
        "soundcloud": "515655",
        "appleMusic": "515655"
      },
      "blendGroup": null
    },
    {
      "pos": "05",
      "artist": "Ray Volpe",
      "title": "Race Against Time (NUU$HI Remix)",
      "remix": "",
      "label": "DISCIPLE",
      "trackId": "7718425",
      "row": 5,
      "type": "normal",
      "cueTime": 0,
      "mediaIds": {
        "spotify": "778185",
        "youtube": "778185",
        "soundcloud": "778185",
        "appleMusic": "778185"
      },
      "blendGroup": null
    },
    {
      "pos": "06",
      "artist": "RZRKT & Antihero",
      "title": "SPAWN",
      "remix": "",
      "label": "SELF RELEASED",
      "trackId": "7718426",
      "row": 6,
      "type": "normal",
      "cueTime": 0,
      "mediaIds": {
        "spotify": "834172",
        "youtube": "834172",
        "soundcloud": "834172",
        "appleMusic": "834172"
      },
      "blendGroup": null
    },
    {
      "pos": "07",
      "artist": "Excision & Wooli & Trivecta ft. Julianne Hope",
      "title": "Oxygen (Ray Volpe Remix)",
      "remix": "",
      "label": "EXCISION",
      "trackId": "7718427",
      "row": 7,
      "type": "normal",
      "cueTime": 0,
      "mediaIds": {
        "spotify": "617582",
        "youtube": "617582",
        "soundcloud": "617582",
        "appleMusic": "617582"
      },
      "blendGroup": null
    },
    {
      "pos": "08",
      "artist": "Excision & Wooli & Trivecta ft. Julianne Hope",
      "title": "Oxygen",
      "remix": "",
      "label": "EXCISION",
      "trackId": "7718428",
      "row": 8,
      "type": "normal",
      "cueTime": 0,
      "mediaIds": {
        "spotify": "525331",
        "youtube": "525331",
        "soundcloud": "525331",
        "appleMusic": "525331"
      },
      "blendGroup": null
    },
    {
      "pos": "09",
      "artist": "Excision & Sullivan King",
      "title": "Unbound",
      "remix": "",
      "label": "SUBSIDIA",
      "trackId": "7718429",
      "row": 9,
      "type": "normal",
      "cueTime": 0,
      "mediaIds": {
        "spotify": "697078",
        "youtube": "697078",
        "soundcloud": "697078",
        "appleMusic": "697078"
      },
      "blendGroup": null
    },
    {
      "pos": "10",
      "artist": "Benda ft. Blupill",
      "title": "Break Shit",
      "remix": "",
      "label": "SUBSIDIA",
      "trackId": "7718430",
      "row": 10,
      "type": "normal",
      "cueTime": 0,
      "mediaIds": {
        "spotify": "746292",
        "youtube": "746292",
        "soundcloud": "746292",
        "appleMusic": "746292"
      },
      "blendGroup": null
    },
    {
      "pos": "11",
      "artist": "JAYSYX",
      "title": "DIAMONDZ",
      "remix": "",
      "label": "SELF RELEASED",
      "trackId": "7718728",
      "row": 11,
      "type": "normal",
      "cueTime": 0,
      "mediaIds": {
        "spotify": "812958",
        "youtube": "812958",
        "soundcloud": "812958",
        "appleMusic": "812958"
      },
      "blendGroup": null
    },
    {
      "pos": "12",
      "artist": "Vastive",
      "title": "Ambience",
      "remix": "",
      "label": "SUBSIDIA",
      "trackId": "7718729",
      "row": 12,
      "type": "normal",
      "cueTime": 0,
      "mediaIds": {
        "spotify": "831982",
        "youtube": "831982",
        "soundcloud": "831982",
        "appleMusic": "831982"
      },
      "blendGroup": null
    },
    {
      "pos": "13",
      "artist": "Jandi",
      "title": "Apollyon",
      "remix": "",
      "label": "SUBSIDIA",
      "trackId": "7718730",
      "row": 13,
      "type": "normal",
      "cueTime": 0,
      "mediaIds": {
        "spotify": "830393",
        "youtube": "830393",
        "soundcloud": "830393",
        "appleMusic": "830393"
      },
      "blendGroup": null
    },
    {
      "pos": "14",
      "artist": "BLVK SHEEP & Chassi",
      "title": "Give Up",
      "remix": "",
      "label": "SUBSIDIA",
      "trackId": "7718731",
      "row": 14,
      "type": "normal",
      "cueTime": 0,
      "mediaIds": null,
      "blendGroup": null
    },
    {
      "pos": "15",
      "artist": "Dr. Ushūu",
      "title": "UNDRGRND",
      "remix": "",
      "label": "DISCIPLE ROUND TABLE",
      "trackId": "7718732",
      "row": 15,
      "type": "normal",
      "cueTime": 0,
      "mediaIds": {
        "spotify": "735109",
        "youtube": "735109",
        "soundcloud": "735109",
        "appleMusic": "735109"
      },
      "blendGroup": null
    },
    {
      "pos": "16",
      "artist": "YOOKiE",
      "title": "Bubble Bass (2Soon Flip)",
      "remix": "",
      "label": "SELF RELEASED",
      "trackId": "7718733",
      "row": 16,
      "type": "normal",
      "cueTime": 0,
      "mediaIds": {
        "youtube": "790344",
        "soundcloud": "790344"
      },
      "blendGroup": null
    },
    {
      "pos": "17",
      "artist": "Stoutty",
      "title": "Back With It",
      "remix": "",
      "label": "SUBSIDIA",
      "trackId": "7719181",
      "row": 17,
      "type": "normal",
      "cueTime": 0,
      "mediaIds": {
        "spotify": "852187",
        "youtube": "852187",
        "soundcloud": "852187",
        "appleMusic": "852187"
      },
      "blendGroup": null
    },
    {
      "pos": "18",
      "artist": "DRINKURWATER",
      "title": "Wet Wet",
      "remix": "",
      "label": "WAKAAN",
      "trackId": "7719182",
      "row": 18,
      "type": "normal",
      "cueTime": 0,
      "mediaIds": {
        "spotify": "790262",
        "youtube": "790262",
        "soundcloud": "790262",
        "appleMusic": "790262"
      },
      "blendGroup": null
    },
    {
      "pos": "19",
      "artist": "Excision",
      "title": "Decimate",
      "remix": "",
      "label": "SUBSIDIA",
      "trackId": "7719183",
      "row": 19,
      "type": "normal",
      "cueTime": 0,
      "mediaIds": {
        "spotify": "734616",
        "youtube": "734616",
        "soundcloud": "734616",
        "appleMusic": "734616"
      },
      "blendGroup": null
    },
    {
      "pos": "20",
      "artist": "AlienPark",
      "title": "ID",
      "remix": "",
      "label": "",
      "trackId": "7719184",
      "row": 20,
      "type": "normal",
      "cueTime": 0,
      "mediaIds": null,
      "blendGroup": null
    },
    {
      "pos": "21",
      "artist": "ID",
      "title": "ID",
      "remix": "",
      "label": "",
      "trackId": "7719185",
      "row": 21,
      "type": "normal",
      "cueTime": 0,
      "mediaIds": null,
      "blendGroup": null
    },
    {
      "pos": "22",
      "artist": "NVRT",
      "title": "CHAOS",
      "remix": "",
      "label": "SELF RELEASED",
      "trackId": "7719186",
      "row": 22,
      "type": "normal",
      "cueTime": 0,
      "mediaIds": {
        "spotify": "830866",
        "soundcloud": "830866",
        "appleMusic": "830866"
      },
      "blendGroup": null
    },
    {
      "pos": "23",
      "artist": "LAYZ & RZRKT",
      "title": "INCOMING",
      "remix": "",
      "label": "BASSWEIGHT",
      "trackId": "7719187",
      "row": 23,
      "type": "normal",
      "cueTime": 0,
      "mediaIds": {
        "spotify": "830865",
        "youtube": "830865",
        "soundcloud": "830865",
        "appleMusic": "830865"
      },
      "blendGroup": null
    },
    {
      "pos": "24",
      "artist": "Vastive",
      "title": "Clench",
      "remix": "",
      "label": "SUBSIDIA",
      "trackId": "7719188",
      "row": 24,
      "type": "normal",
      "cueTime": 0,
      "mediaIds": {
        "spotify": "830488",
        "youtube": "830488",
        "soundcloud": "830488",
        "appleMusic": "830488"
      },
      "blendGroup": null
    },
    {
      "pos": "25",
      "artist": "RZRKT",
      "title": "REBORN",
      "remix": "",
      "label": "SUBSIDIA",
      "trackId": "7719189",
      "row": 25,
      "type": "normal",
      "cueTime": 0,
      "mediaIds": {
        "spotify": "811398",
        "youtube": "811398",
        "soundcloud": "811398",
        "appleMusic": "811398"
      },
      "blendGroup": null
    },
    {
      "pos": "26",
      "artist": "Storyboard & EVVDE",
      "title": "Dyad",
      "remix": "",
      "label": "REPOST NETWORK",
      "trackId": "7719190",
      "row": 26,
      "type": "normal",
      "cueTime": 0,
      "mediaIds": {
        "spotify": "707538",
        "youtube": "707538",
        "soundcloud": "707538",
        "appleMusic": "707538"
      },
      "blendGroup": null
    },
    {
      "pos": "27",
      "artist": "AlienPark",
      "title": "System Damage",
      "remix": "",
      "label": "SUBSIDIA",
      "trackId": "7719191",
      "row": 27,
      "type": "normal",
      "cueTime": 0,
      "mediaIds": {
        "spotify": "789671",
        "youtube": "789671",
        "soundcloud": "789671",
        "appleMusic": "789671"
      },
      "blendGroup": null
    },
    {
      "pos": "28",
      "artist": "Excision & Dion Timmer ft. Alexis Donn",
      "title": "Salvation",
      "remix": "",
      "label": "SUBSIDIA",
      "trackId": "7719192",
      "row": 28,
      "type": "normal",
      "cueTime": 0,
      "mediaIds": {
        "spotify": "702741",
        "youtube": "702741",
        "soundcloud": "702741",
        "appleMusic": "702741"
      },
      "blendGroup": null
    },
    {
      "pos": "29",
      "artist": "Excision & Dion Timmer",
      "title": "Time Stood Still (VIP)",
      "remix": "",
      "label": "SUBSIDIA",
      "trackId": "7719193",
      "row": 29,
      "type": "normal",
      "cueTime": 0,
      "mediaIds": {
        "spotify": "710302",
        "youtube": "710302",
        "soundcloud": "710302",
        "appleMusic": "710302"
      },
      "blendGroup": null
    },
    {
      "pos": "30",
      "artist": "Excision",
      "title": "Reborn",
      "remix": "",
      "label": "SUBSIDIA",
      "trackId": "7719194",
      "row": 30,
      "type": "normal",
      "cueTime": 0,
      "mediaIds": {
        "spotify": "704077",
        "youtube": "704077",
        "soundcloud": "704077",
        "appleMusic": "704077"
      },
      "blendGroup": null
    },
    {
      "pos": "31",
      "artist": "ID",
      "title": "ID",
      "remix": "",
      "label": "",
      "trackId": "7719195",
      "row": 31,
      "type": "normal",
      "cueTime": 0,
      "mediaIds": null,
      "blendGroup": null
    }
  ],
  "recordings": [
    {
      "platform": "soundcloud",
      "idMedia": "4653140",
      "idSource": "10",
      "url": "https://api.soundcloud.com/tracks/1274779528"
    },
    {
      "platform": "youtube",
      "idMedia": "2816920",
      "idSource": "13",
      "url": "https://www.youtube.com/watch?v=jx00bnG9k_g"
    },
    {
      "platform": "hearthis",
      "idMedia": "2816799",
      "idSource": "40",
      "url": "https://hearthis.at/6773344/"
    }
  ],
  "scrapedAt": "2026-04-08T04:46:03.844Z",
  "scrapeVersion": 2
}